tholos_utils/__init__.py
tholos_utils/utils.py
tholos_utils-1.0.3.dist-info/LICENSE
tholos_utils-1.0.3.dist-info/METADATA
tholos_utils-1.0.3.dist-info/WHEEL
tholos_utils-1.0.3.dist-info/top_level.txt
tholos_utils-1.0.3.dist-info/RECORD
