Metadata-Version: 2.1
Name: tholos-utils
Version: 1.0.3
Summary: Tholos python utils
Home-page: https://github.com/tholos-inc/tholos-utils
Author: Tholos Devs
Author-email: bryan@tholos.app
Project-URL: Bug Tracker, https://github.com/tholos-inc/tholos/issues
Project-URL: repository, https://github.com/tholos-inc/tholos
Classifier: Programming Language :: Python :: 3
Classifier: License :: OSI Approved :: Apache Software License
Classifier: Operating System :: OS Independent
Requires-Python: >=3.9
License-File: LICENSE
Requires-Dist: boto3 (==1.26.64)
Requires-Dist: psycopg2-binary (==2.9.5)
